{
  "id": 41,
  "name": "",
  "title": "",
  "rarity": 3,
  "element": 1,
  "vocation": 6,
  "affiliation": 40019,
  "age": "25",
  "artist": "",
  "artistOverseas": "",
  "backstories": [
    "",
    "",
    "",
    ""
  ],
  "birthday": "",
  "height": "179cm",
  "hobby": "",
  "race": "Human",
  "sex": "",
  "unlockCondition": [],
  "weight": "？",
  "skins": [
    {
      "id": 904101,
      "name": "",
      "description": "",
      "artist": "",
      "overseasArtist": "",
      "card": "/ui/imagesets/cards//Card_043.png",
      "diamond": "/ui/imagesets/headphotos//headphoto_43.png",
      "gacha": "/ui/imagesets/headphotos//hpg_043.png",
      "longCard": "/ui/imagesets/headphotos//hpl_043.png",
      "round": "/ui/imagesets/headphotos//BattleChar_43.png",
      "square": "/ui/imagesets/headphotos//hp_043.png",
      "stone": null,
      "team": "/ui/imagesets/headphotos//hpc_043.png",
      "pixelAnims": [],
      "l2d": null
    },
    {
      "id": 904102,
      "name": "",
      "description": "",
      "artist": "",
      "overseasArtist": "",
      "card": "/ui/imagesets/cards//Card_043.png",
      "diamond": "/ui/imagesets/headphotos//headphoto_43.png",
      "gacha": "/ui/imagesets/headphotos//hpg_043.png",
      "longCard": "/ui/imagesets/headphotos//hpl_043.png",
      "round": "/ui/imagesets/headphotos//BattleChar_43.png",
      "square": "/ui/imagesets/headphotos//hp_043.png",
      "stone": null,
      "team": "/ui/imagesets/headphotos//hpc_043.png",
      "pixelAnims": [],
      "l2d": {
        "name": "char043",
        "url": "/overseas_live2d/char043"
      }
    },
    {
      "id": 904103,
      "name": "",
      "description": "",
      "artist": "",
      "overseasArtist": "",
      "card": "/ui/imagesets/cards//Card_043b.png",
      "diamond": "/ui/imagesets/headphotos//headphoto_43b.png",
      "gacha": null,
      "longCard": "/ui/imagesets/headphotos//hpl_043b.png",
      "round": "/ui/imagesets/headphotos//BattleChar_43b.png",
      "square": "/ui/imagesets/headphotos//hp_043b.png",
      "stone": null,
      "team": "/ui/imagesets/headphotos//hpc_043b.png",
      "pixelAnims": [],
      "l2d": {
        "name": "char043_break",
        "url": "/overseas_live2d/char043_break"
      }
    },
    {
      "id": 904111,
      "name": "",
      "description": "",
      "artist": "",
      "overseasArtist": "",
      "card": "/ui/imagesets/localization/role/char_043_v1//card.png",
      "diamond": "/ui/imagesets/localization/role/char_043_v1//diamond.png",
      "gacha": null,
      "longCard": "/ui/imagesets/localization/role/char_043_v1//longcard.png",
      "round": "/ui/imagesets/localization/role/char_043_v1//round.png",
      "square": "/ui/imagesets/localization/role/char_043_v1//square.png",
      "stone": null,
      "team": "/ui/imagesets/localization/role/char_043_v1//team.png",
      "pixelAnims": [],
      "l2d": {
        "name": "char043_v1",
        "url": "/overseas_live2d/char043_v1"
      }
    }
  ],
  "roleLine": null,
  "victoryTalk": null,
  "damageType": 2,
  "evolutionLimit": 3,
  "baseStats": {
    "atkspeed": 100,
    "attack": 125,
    "def": 21,
    "hp": 436,
    "magicDef": 23,
    "speed": 30
  },
  "growthStats": {
    "atkspeed": 0,
    "attack": 12.57,
    "def": 2.17,
    "hp": 43.61,
    "magicDef": 2.39,
    "speed": 2.4
  },
  "breakStats": {
    "attack": 12.57,
    "def": 2.17,
    "hp": 43.61,
    "magicDef": 2.39
  },
  "skills": [
    {
      "id": 60411,
      "type": "assist"
    },
    {
      "id": 60411,
      "type": "contract"
    },
    {
      "id": 60412,
      "type": "contract"
    },
    {
      "id": 504101,
      "type": "contract"
    },
    {
      "id": 3003,
      "type": "yard"
    }
  ],
  "uniqueEquipment": 95041,
  "gifts": [
    31014,
    31015,
    31016
  ],
  "roleEquipType": "6;8",
  "shapeID": 1047
}