{
  "id": 9,
  "name": "",
  "title": "",
  "rarity": 1,
  "element": 3,
  "vocation": 5,
  "affiliation": 40016,
  "age": "18",
  "artist": "",
  "artistOverseas": "",
  "backstories": [
    "",
    "",
    "",
    ""
  ],
  "birthday": "",
  "height": "155cm",
  "hobby": "",
  "race": "Human",
  "sex": "",
  "unlockCondition": [],
  "weight": "？",
  "skins": [
    {
      "id": 900901,
      "name": "",
      "description": "",
      "artist": "",
      "overseasArtist": "",
      "card": "/ui/imagesets/cards//Card_020.png",
      "diamond": "/ui/imagesets/headphotos//headphoto_20.png",
      "gacha": "/ui/imagesets/headphotos//hpg_020.png",
      "longCard": "/ui/imagesets/headphotos//hpl_020.png",
      "round": "/ui/imagesets/headphotos//BattleChar_20.png",
      "square": "/ui/imagesets/headphotos//hp_020.png",
      "stone": null,
      "team": "/ui/imagesets/headphotos//hpc_020.png",
      "pixelAnims": [],
      "l2d": null
    },
    {
      "id": 900902,
      "name": "",
      "description": "",
      "artist": "",
      "overseasArtist": "",
      "card": "/ui/imagesets/cards//Card_020.png",
      "diamond": "/ui/imagesets/headphotos//headphoto_20.png",
      "gacha": "/ui/imagesets/headphotos//hpg_020.png",
      "longCard": "/ui/imagesets/headphotos//hpl_020.png",
      "round": "/ui/imagesets/headphotos//BattleChar_20.png",
      "square": "/ui/imagesets/headphotos//hp_020.png",
      "stone": null,
      "team": "/ui/imagesets/headphotos//hpc_020.png",
      "pixelAnims": [],
      "l2d": {
        "name": "char020",
        "url": "/overseas_live2d/char020"
      }
    }
  ],
  "roleLine": null,
  "victoryTalk": null,
  "damageType": 2,
  "evolutionLimit": 3,
  "baseStats": {
    "atkspeed": 100,
    "attack": 76,
    "def": 20,
    "hp": 382,
    "magicDef": 2,
    "speed": 25
  },
  "growthStats": {
    "atkspeed": 0,
    "attack": 7.65,
    "def": 2.04,
    "hp": 38.25,
    "magicDef": 0.2,
    "speed": 2
  },
  "breakStats": {
    "attack": 7.65,
    "def": 2.04,
    "hp": 38.25,
    "magicDef": 0.2
  },
  "skills": [
    {
      "id": 60092,
      "type": "assist"
    },
    {
      "id": 60091,
      "type": "contract"
    },
    {
      "id": 60092,
      "type": "contract"
    },
    {
      "id": 500901,
      "type": "contract"
    },
    {
      "id": 3001,
      "type": "yard"
    }
  ],
  "uniqueEquipment": 0,
  "gifts": [
    31008,
    31009,
    31010
  ],
  "roleEquipType": "5;8",
  "shapeID": 1019
}