{
  "id": 123,
  "name": "",
  "title": "",
  "rarity": 4,
  "element": 3,
  "vocation": 4,
  "affiliation": 40015,
  "age": "？",
  "artist": "",
  "artistOverseas": "",
  "backstories": [
    "",
    "",
    "",
    ""
  ],
  "birthday": "",
  "height": "161cm",
  "hobby": "",
  "race": "Human",
  "sex": "",
  "unlockCondition": [],
  "weight": "？",
  "skins": [
    {
      "id": 912301,
      "name": "",
      "description": "",
      "artist": "",
      "overseasArtist": "",
      "card": "/ui/imagesets/localization/role/char_123//card.png",
      "diamond": "/ui/imagesets/localization/role/char_123//diamond.png",
      "gacha": "/ui/imagesets/localization/role/char_123//gacha.png",
      "longCard": "/ui/imagesets/localization/role/char_123//longcard.png",
      "round": "/ui/imagesets/localization/role/char_123//round.png",
      "square": "/ui/imagesets/localization/role/char_123//square.png",
      "stone": null,
      "team": "/ui/imagesets/localization/role/char_123//team.png",
      "pixelAnims": [],
      "l2d": null
    },
    {
      "id": 912302,
      "name": "",
      "description": "",
      "artist": "",
      "overseasArtist": "",
      "card": "/ui/imagesets/localization/role/char_123//card.png",
      "diamond": "/ui/imagesets/localization/role/char_123//diamond.png",
      "gacha": "/ui/imagesets/localization/role/char_123//gacha.png",
      "longCard": "/ui/imagesets/localization/role/char_123//longcard.png",
      "round": "/ui/imagesets/localization/role/char_123//round.png",
      "square": "/ui/imagesets/localization/role/char_123//square.png",
      "stone": null,
      "team": "/ui/imagesets/localization/role/char_123//team.png",
      "pixelAnims": [],
      "l2d": {
        "name": "char123",
        "url": "/overseas_live2d/char123"
      }
    },
    {
      "id": 912303,
      "name": "",
      "description": "",
      "artist": "",
      "overseasArtist": "",
      "card": "/ui/imagesets/localization/role/char_123_break//card.png",
      "diamond": "/ui/imagesets/localization/role/char_123_break//diamond.png",
      "gacha": null,
      "longCard": "/ui/imagesets/localization/role/char_123_break//longcard.png",
      "round": "/ui/imagesets/localization/role/char_123_break//round.png",
      "square": "/ui/imagesets/localization/role/char_123_break//square.png",
      "stone": null,
      "team": "/ui/imagesets/localization/role/char_123_break//team.png",
      "pixelAnims": [],
      "l2d": {
        "name": "char123_break",
        "url": "/overseas_live2d/char123_break"
      }
    }
  ],
  "roleLine": null,
  "victoryTalk": null,
  "damageType": 2,
  "evolutionLimit": 3,
  "baseStats": {
    "atkspeed": 100,
    "attack": 90,
    "def": 24,
    "hp": 450,
    "magicDef": 24,
    "speed": 30
  },
  "growthStats": {
    "atkspeed": 0,
    "attack": 9,
    "def": 2.4,
    "hp": 45,
    "magicDef": 2.4,
    "speed": 2.4
  },
  "breakStats": {
    "attack": 9,
    "def": 2.4,
    "hp": 45,
    "magicDef": 2.4
  },
  "skills": [
    {
      "id": 61232,
      "type": "assist"
    },
    {
      "id": 61231,
      "type": "contract"
    },
    {
      "id": 61232,
      "type": "contract"
    },
    {
      "id": 512301,
      "type": "contract"
    },
    {
      "id": 2003,
      "type": "yard"
    }
  ],
  "uniqueEquipment": 95123,
  "gifts": [
    31011,
    31012,
    31013
  ],
  "roleEquipType": "4;8",
  "shapeID": 1134
}