[
  {
    "id": 31,
    "name": "Contact from the Otherworld",
    "description": "Have 1 friend",
    "group": "Social",
    "points": 10,
    "rewards": [
      {
        "item": {
          "id": 35008,
          "name": "Soul",
          "description": "Crystallized by magic, it is necessary for any Witch who intends to sign a Soul Contract. $B$$B$Used to summon new Dolls",
          "icon": "/rw/assets/GLOBAL/ui/imagesets/items1//100191.png",
          "type": "Currency"
        },
        "amount": 40
      },
      {
        "item": {
          "id": 31070,
          "name": "Achievement Badge",
          "description": "Upon completion of this achievement, you will obtain a badge.",
          "icon": "/rw/assets/GLOBAL/ui/imagesets/items1//100543.png",
          "type": "Normal Item"
        },
        "amount": 1
      }
    ]
  },
  {
    "id": 0,
    "name": "Step into the Otherworld",
    "description": "Defeat the Dimension Overseer",
    "group": "Progress",
    "points": 10,
    "rewards": [
      {
        "item": {
          "id": 35008,
          "name": "Soul",
          "description": "Crystallized by magic, it is necessary for any Witch who intends to sign a Soul Contract. $B$$B$Used to summon new Dolls",
          "icon": "/rw/assets/GLOBAL/ui/imagesets/items1//100191.png",
          "type": "Currency"
        },
        "amount": 40
      }
    ]
  },
  {
    "id": 0,
    "name": "Flare Shattered",
    "description": "Defeat Flare",
    "group": "Progress",
    "points": 10,
    "rewards": [
      {
        "item": {
          "id": 35008,
          "name": "Soul",
          "description": "Crystallized by magic, it is necessary for any Witch who intends to sign a Soul Contract. $B$$B$Used to summon new Dolls",
          "icon": "/rw/assets/GLOBAL/ui/imagesets/items1//100191.png",
          "type": "Currency"
        },
        "amount": 40
      }
    ]
  },
  {
    "id": 0,
    "name": "Save Irminsul",
    "description": "Defeat Asherah",
    "group": "Progress",
    "points": 10,
    "rewards": [
      {
        "item": {
          "id": 35008,
          "name": "Soul",
          "description": "Crystallized by magic, it is necessary for any Witch who intends to sign a Soul Contract. $B$$B$Used to summon new Dolls",
          "icon": "/rw/assets/GLOBAL/ui/imagesets/items1//100191.png",
          "type": "Currency"
        },
        "amount": 80
      }
    ]
  },
  {
    "id": 0,
    "name": "Ferocious Bear",
    "description": "Defeat Hervoraltar",
    "group": "Progress",
    "points": 10,
    "rewards": [
      {
        "item": {
          "id": 35008,
          "name": "Soul",
          "description": "Crystallized by magic, it is necessary for any Witch who intends to sign a Soul Contract. $B$$B$Used to summon new Dolls",
          "icon": "/rw/assets/GLOBAL/ui/imagesets/items1//100191.png",
          "type": "Currency"
        },
        "amount": 40
      }
    ]
  },
  {
    "id": 0,
    "name": "Blizzard Rest",
    "description": "Defeat Cersivey",
    "group": "Progress",
    "points": 10,
    "rewards": [
      {
        "item": {
          "id": 35008,
          "name": "Soul",
          "description": "Crystallized by magic, it is necessary for any Witch who intends to sign a Soul Contract. $B$$B$Used to summon new Dolls",
          "icon": "/rw/assets/GLOBAL/ui/imagesets/items1//100191.png",
          "type": "Currency"
        },
        "amount": 80
      }
    ]
  },
  {
    "id": 0,
    "name": "Save Snegurochka",
    "description": "Defeat Sinmara",
    "group": "Progress",
    "points": 10,
    "rewards": [
      {
        "item": {
          "id": 35008,
          "name": "Soul",
          "description": "Crystallized by magic, it is necessary for any Witch who intends to sign a Soul Contract. $B$$B$Used to summon new Dolls",
          "icon": "/rw/assets/GLOBAL/ui/imagesets/items1//100191.png",
          "type": "Currency"
        },
        "amount": 80
      }
    ]
  },
  {
    "id": 0,
    "name": "Chest Gatherer",
    "description": "Open 100 Chests",
    "group": "Progress",
    "points": 10,
    "rewards": [
      {
        "item": {
          "id": 35008,
          "name": "Soul",
          "description": "Crystallized by magic, it is necessary for any Witch who intends to sign a Soul Contract. $B$$B$Used to summon new Dolls",
          "icon": "/rw/assets/GLOBAL/ui/imagesets/items1//100191.png",
          "type": "Currency"
        },
        "amount": 80
      }
    ]
  },
  {
    "id": 0,
    "name": "Chest Gatherer",
    "description": "Open 500 Chests",
    "group": "Progress",
    "points": 10,
    "rewards": [
      {
        "item": {
          "id": 35008,
          "name": "Soul",
          "description": "Crystallized by magic, it is necessary for any Witch who intends to sign a Soul Contract. $B$$B$Used to summon new Dolls",
          "icon": "/rw/assets/GLOBAL/ui/imagesets/items1//100191.png",
          "type": "Currency"
        },
        "amount": 200
      }
    ]
  },
  {
    "id": 0,
    "name": "Mana Gatherer",
    "description": "Crack 50 Mana Crystal Clusters",
    "group": "Progress",
    "points": 10,
    "rewards": [
      {
        "item": {
          "id": 35008,
          "name": "Soul",
          "description": "Crystallized by magic, it is necessary for any Witch who intends to sign a Soul Contract. $B$$B$Used to summon new Dolls",
          "icon": "/rw/assets/GLOBAL/ui/imagesets/items1//100191.png",
          "type": "Currency"
        },
        "amount": 80
      }
    ]
  },
  {
    "id": 0,
    "name": "Mana Gatherer",
    "description": "Crack 250 Mana Crystal Clusters",
    "group": "Progress",
    "points": 10,
    "rewards": [
      {
        "item": {
          "id": 35008,
          "name": "Soul",
          "description": "Crystallized by magic, it is necessary for any Witch who intends to sign a Soul Contract. $B$$B$Used to summon new Dolls",
          "icon": "/rw/assets/GLOBAL/ui/imagesets/items1//100191.png",
          "type": "Currency"
        },
        "amount": 200
      }
    ]
  },
  {
    "id": 7,
    "name": "Monster Hunter",
    "description": "Defeat 50 monsters",
    "group": "Progress",
    "points": 10,
    "rewards": [
      {
        "item": {
          "id": 35008,
          "name": "Soul",
          "description": "Crystallized by magic, it is necessary for any Witch who intends to sign a Soul Contract. $B$$B$Used to summon new Dolls",
          "icon": "/rw/assets/GLOBAL/ui/imagesets/items1//100191.png",
          "type": "Currency"
        },
        "amount": 40
      },
      {
        "item": {
          "id": 31070,
          "name": "Achievement Badge",
          "description": "Upon completion of this achievement, you will obtain a badge.",
          "icon": "/rw/assets/GLOBAL/ui/imagesets/items1//100543.png",
          "type": "Normal Item"
        },
        "amount": 1
      }
    ]
  },
  {
    "id": 8,
    "name": "Monster Hunter",
    "description": "Defeat 500 monsters",
    "group": "Progress",
    "points": 10,
    "rewards": [
      {
        "item": {
          "id": 35008,
          "name": "Soul",
          "description": "Crystallized by magic, it is necessary for any Witch who intends to sign a Soul Contract. $B$$B$Used to summon new Dolls",
          "icon": "/rw/assets/GLOBAL/ui/imagesets/items1//100191.png",
          "type": "Currency"
        },
        "amount": 80
      },
      {
        "item": {
          "id": 31070,
          "name": "Achievement Badge",
          "description": "Upon completion of this achievement, you will obtain a badge.",
          "icon": "/rw/assets/GLOBAL/ui/imagesets/items1//100543.png",
          "type": "Normal Item"
        },
        "amount": 1
      }
    ]
  },
  {
    "id": 9,
    "name": "Monster Hunter",
    "description": "Defeat 2,000 monsters",
    "group": "Progress",
    "points": 10,
    "rewards": [
      {
        "item": {
          "id": 35008,
          "name": "Soul",
          "description": "Crystallized by magic, it is necessary for any Witch who intends to sign a Soul Contract. $B$$B$Used to summon new Dolls",
          "icon": "/rw/assets/GLOBAL/ui/imagesets/items1//100191.png",
          "type": "Currency"
        },
        "amount": 200
      },
      {
        "item": {
          "id": 31070,
          "name": "Achievement Badge",
          "description": "Upon completion of this achievement, you will obtain a badge.",
          "icon": "/rw/assets/GLOBAL/ui/imagesets/items1//100543.png",
          "type": "Normal Item"
        },
        "amount": 1
      }
    ]
  },
  {
    "id": 13,
    "name": "Magic Convergence",
    "description": "Obtain 100,000 Mana",
    "group": "Growth",
    "points": 10,
    "rewards": [
      {
        "item": {
          "id": 35008,
          "name": "Soul",
          "description": "Crystallized by magic, it is necessary for any Witch who intends to sign a Soul Contract. $B$$B$Used to summon new Dolls",
          "icon": "/rw/assets/GLOBAL/ui/imagesets/items1//100191.png",
          "type": "Currency"
        },
        "amount": 40
      },
      {
        "item": {
          "id": 31070,
          "name": "Achievement Badge",
          "description": "Upon completion of this achievement, you will obtain a badge.",
          "icon": "/rw/assets/GLOBAL/ui/imagesets/items1//100543.png",
          "type": "Normal Item"
        },
        "amount": 1
      }
    ]
  },
  {
    "id": 14,
    "name": "Magic Convergence",
    "description": "Obtain 5,000,000 Mana",
    "group": "Growth",
    "points": 10,
    "rewards": [
      {
        "item": {
          "id": 35008,
          "name": "Soul",
          "description": "Crystallized by magic, it is necessary for any Witch who intends to sign a Soul Contract. $B$$B$Used to summon new Dolls",
          "icon": "/rw/assets/GLOBAL/ui/imagesets/items1//100191.png",
          "type": "Currency"
        },
        "amount": 80
      },
      {
        "item": {
          "id": 31070,
          "name": "Achievement Badge",
          "description": "Upon completion of this achievement, you will obtain a badge.",
          "icon": "/rw/assets/GLOBAL/ui/imagesets/items1//100543.png",
          "type": "Normal Item"
        },
        "amount": 1
      }
    ]
  },
  {
    "id": 15,
    "name": "Magic Convergence",
    "description": "Obtain 50,000,000 Mana",
    "group": "Growth",
    "points": 10,
    "rewards": [
      {
        "item": {
          "id": 35008,
          "name": "Soul",
          "description": "Crystallized by magic, it is necessary for any Witch who intends to sign a Soul Contract. $B$$B$Used to summon new Dolls",
          "icon": "/rw/assets/GLOBAL/ui/imagesets/items1//100191.png",
          "type": "Currency"
        },
        "amount": 500
      },
      {
        "item": {
          "id": 31070,
          "name": "Achievement Badge",
          "description": "Upon completion of this achievement, you will obtain a badge.",
          "icon": "/rw/assets/GLOBAL/ui/imagesets/items1//100543.png",
          "type": "Normal Item"
        },
        "amount": 1
      }
    ]
  },
  {
    "id": 0,
    "name": "Equipment Gatherer",
    "description": "Obtain 20 pieces of equipment",
    "group": "Growth",
    "points": 10,
    "rewards": [
      {
        "item": {
          "id": 35008,
          "name": "Soul",
          "description": "Crystallized by magic, it is necessary for any Witch who intends to sign a Soul Contract. $B$$B$Used to summon new Dolls",
          "icon": "/rw/assets/GLOBAL/ui/imagesets/items1//100191.png",
          "type": "Currency"
        },
        "amount": 40
      }
    ]
  },
  {
    "id": 0,
    "name": "Equipment Gatherer",
    "description": "Obtain 200 pieces of equipment",
    "group": "Growth",
    "points": 10,
    "rewards": [
      {
        "item": {
          "id": 35008,
          "name": "Soul",
          "description": "Crystallized by magic, it is necessary for any Witch who intends to sign a Soul Contract. $B$$B$Used to summon new Dolls",
          "icon": "/rw/assets/GLOBAL/ui/imagesets/items1//100191.png",
          "type": "Currency"
        },
        "amount": 80
      }
    ]
  },
  {
    "id": 0,
    "name": "Equipment Gatherer",
    "description": "Obtain 500 pieces of equipment",
    "group": "Growth",
    "points": 10,
    "rewards": [
      {
        "item": {
          "id": 35008,
          "name": "Soul",
          "description": "Crystallized by magic, it is necessary for any Witch who intends to sign a Soul Contract. $B$$B$Used to summon new Dolls",
          "icon": "/rw/assets/GLOBAL/ui/imagesets/items1//100191.png",
          "type": "Currency"
        },
        "amount": 500
      }
    ]
  },
  {
    "id": 0,
    "name": "Dreamworld",
    "description": "Clear all stages of Dreamworld",
    "group": "Growth",
    "points": 10,
    "rewards": [
      {
        "item": {
          "id": 35008,
          "name": "Soul",
          "description": "Crystallized by magic, it is necessary for any Witch who intends to sign a Soul Contract. $B$$B$Used to summon new Dolls",
          "icon": "/rw/assets/GLOBAL/ui/imagesets/items1//100191.png",
          "type": "Currency"
        },
        "amount": 200
      }
    ]
  },
  {
    "id": 0,
    "name": "Combat Tactic",
    "description": "Disrupt enemy's spell 1 time",
    "group": "Progress",
    "points": 10,
    "rewards": [
      {
        "item": {
          "id": 35008,
          "name": "Soul",
          "description": "Crystallized by magic, it is necessary for any Witch who intends to sign a Soul Contract. $B$$B$Used to summon new Dolls",
          "icon": "/rw/assets/GLOBAL/ui/imagesets/items1//100191.png",
          "type": "Currency"
        },
        "amount": 40
      }
    ]
  },
  {
    "id": 28,
    "name": "Ascend Limit",
    "description": "3 Dolls reach Ascension 1",
    "group": "Growth",
    "points": 10,
    "rewards": [
      {
        "item": {
          "id": 35008,
          "name": "Soul",
          "description": "Crystallized by magic, it is necessary for any Witch who intends to sign a Soul Contract. $B$$B$Used to summon new Dolls",
          "icon": "/rw/assets/GLOBAL/ui/imagesets/items1//100191.png",
          "type": "Currency"
        },
        "amount": 40
      },
      {
        "item": {
          "id": 31070,
          "name": "Achievement Badge",
          "description": "Upon completion of this achievement, you will obtain a badge.",
          "icon": "/rw/assets/GLOBAL/ui/imagesets/items1//100543.png",
          "type": "Normal Item"
        },
        "amount": 1
      }
    ]
  },
  {
    "id": 29,
    "name": "Ascend Limit",
    "description": "3 Dolls reach Ascension 2",
    "group": "Growth",
    "points": 10,
    "rewards": [
      {
        "item": {
          "id": 35008,
          "name": "Soul",
          "description": "Crystallized by magic, it is necessary for any Witch who intends to sign a Soul Contract. $B$$B$Used to summon new Dolls",
          "icon": "/rw/assets/GLOBAL/ui/imagesets/items1//100191.png",
          "type": "Currency"
        },
        "amount": 80
      },
      {
        "item": {
          "id": 31070,
          "name": "Achievement Badge",
          "description": "Upon completion of this achievement, you will obtain a badge.",
          "icon": "/rw/assets/GLOBAL/ui/imagesets/items1//100543.png",
          "type": "Normal Item"
        },
        "amount": 1
      }
    ]
  },
  {
    "id": 30,
    "name": "Ascend Limit",
    "description": "3 Dolls reach Ascension 3",
    "group": "Growth",
    "points": 10,
    "rewards": [
      {
        "item": {
          "id": 35008,
          "name": "Soul",
          "description": "Crystallized by magic, it is necessary for any Witch who intends to sign a Soul Contract. $B$$B$Used to summon new Dolls",
          "icon": "/rw/assets/GLOBAL/ui/imagesets/items1//100191.png",
          "type": "Currency"
        },
        "amount": 200
      },
      {
        "item": {
          "id": 31070,
          "name": "Achievement Badge",
          "description": "Upon completion of this achievement, you will obtain a badge.",
          "icon": "/rw/assets/GLOBAL/ui/imagesets/items1//100543.png",
          "type": "Normal Item"
        },
        "amount": 1
      }
    ]
  },
  {
    "id": 0,
    "name": "Ascend Limit",
    "description": "3 Dolls reach Ascension 4",
    "group": "Growth",
    "points": 10,
    "rewards": [
      {
        "item": {
          "id": 35008,
          "name": "Soul",
          "description": "Crystallized by magic, it is necessary for any Witch who intends to sign a Soul Contract. $B$$B$Used to summon new Dolls",
          "icon": "/rw/assets/GLOBAL/ui/imagesets/items1//100191.png",
          "type": "Currency"
        },
        "amount": 500
      }
    ]
  },
  {
    "id": 0,
    "name": "Power of Evolution",
    "description": "1 Doll reaches Evolution 1",
    "group": "Growth",
    "points": 10,
    "rewards": [
      {
        "item": {
          "id": 35008,
          "name": "Soul",
          "description": "Crystallized by magic, it is necessary for any Witch who intends to sign a Soul Contract. $B$$B$Used to summon new Dolls",
          "icon": "/rw/assets/GLOBAL/ui/imagesets/items1//100191.png",
          "type": "Currency"
        },
        "amount": 40
      }
    ]
  },
  {
    "id": 0,
    "name": "Power of Evolution",
    "description": "3 Dolls reach Evolution 2",
    "group": "Growth",
    "points": 10,
    "rewards": [
      {
        "item": {
          "id": 35008,
          "name": "Soul",
          "description": "Crystallized by magic, it is necessary for any Witch who intends to sign a Soul Contract. $B$$B$Used to summon new Dolls",
          "icon": "/rw/assets/GLOBAL/ui/imagesets/items1//100191.png",
          "type": "Currency"
        },
        "amount": 80
      }
    ]
  },
  {
    "id": 0,
    "name": "Power of Evolution",
    "description": "6 Dolls reach Evolution 3",
    "group": "Growth",
    "points": 10,
    "rewards": [
      {
        "item": {
          "id": 35008,
          "name": "Soul",
          "description": "Crystallized by magic, it is necessary for any Witch who intends to sign a Soul Contract. $B$$B$Used to summon new Dolls",
          "icon": "/rw/assets/GLOBAL/ui/imagesets/items1//100191.png",
          "type": "Currency"
        },
        "amount": 500
      }
    ]
  },
  {
    "id": 0,
    "name": "Doll Gatherer",
    "description": "Have 10 Dolls",
    "group": "Bond",
    "points": 10,
    "rewards": [
      {
        "item": {
          "id": 35008,
          "name": "Soul",
          "description": "Crystallized by magic, it is necessary for any Witch who intends to sign a Soul Contract. $B$$B$Used to summon new Dolls",
          "icon": "/rw/assets/GLOBAL/ui/imagesets/items1//100191.png",
          "type": "Currency"
        },
        "amount": 40
      }
    ]
  },
  {
    "id": 0,
    "name": "Doll Gatherer",
    "description": "Have 30 Dolls",
    "group": "Bond",
    "points": 10,
    "rewards": [
      {
        "item": {
          "id": 35008,
          "name": "Soul",
          "description": "Crystallized by magic, it is necessary for any Witch who intends to sign a Soul Contract. $B$$B$Used to summon new Dolls",
          "icon": "/rw/assets/GLOBAL/ui/imagesets/items1//100191.png",
          "type": "Currency"
        },
        "amount": 200
      }
    ]
  },
  {
    "id": 0,
    "name": "Doll Gatherer",
    "description": "Have 50 Dolls",
    "group": "Bond",
    "points": 10,
    "rewards": [
      {
        "item": {
          "id": 35008,
          "name": "Soul",
          "description": "Crystallized by magic, it is necessary for any Witch who intends to sign a Soul Contract. $B$$B$Used to summon new Dolls",
          "icon": "/rw/assets/GLOBAL/ui/imagesets/items1//100191.png",
          "type": "Currency"
        },
        "amount": 500
      }
    ]
  },
  {
    "id": 4,
    "name": "Bond Together",
    "description": "Upgrade the Bond Level of a Doll to Lv.2",
    "group": "Bond",
    "points": 10,
    "rewards": [
      {
        "item": {
          "id": 35008,
          "name": "Soul",
          "description": "Crystallized by magic, it is necessary for any Witch who intends to sign a Soul Contract. $B$$B$Used to summon new Dolls",
          "icon": "/rw/assets/GLOBAL/ui/imagesets/items1//100191.png",
          "type": "Currency"
        },
        "amount": 40
      },
      {
        "item": {
          "id": 31070,
          "name": "Achievement Badge",
          "description": "Upon completion of this achievement, you will obtain a badge.",
          "icon": "/rw/assets/GLOBAL/ui/imagesets/items1//100543.png",
          "type": "Normal Item"
        },
        "amount": 1
      }
    ]
  },
  {
    "id": 5,
    "name": "Bond Together",
    "description": "Upgrade the Bond Level of a Doll to Lv.10",
    "group": "Bond",
    "points": 10,
    "rewards": [
      {
        "item": {
          "id": 35008,
          "name": "Soul",
          "description": "Crystallized by magic, it is necessary for any Witch who intends to sign a Soul Contract. $B$$B$Used to summon new Dolls",
          "icon": "/rw/assets/GLOBAL/ui/imagesets/items1//100191.png",
          "type": "Currency"
        },
        "amount": 80
      },
      {
        "item": {
          "id": 31070,
          "name": "Achievement Badge",
          "description": "Upon completion of this achievement, you will obtain a badge.",
          "icon": "/rw/assets/GLOBAL/ui/imagesets/items1//100543.png",
          "type": "Normal Item"
        },
        "amount": 1
      }
    ]
  },
  {
    "id": 6,
    "name": "Bond Together",
    "description": "Upgrade the Bond Level of a Doll to Lv.20",
    "group": "Bond",
    "points": 10,
    "rewards": [
      {
        "item": {
          "id": 35008,
          "name": "Soul",
          "description": "Crystallized by magic, it is necessary for any Witch who intends to sign a Soul Contract. $B$$B$Used to summon new Dolls",
          "icon": "/rw/assets/GLOBAL/ui/imagesets/items1//100191.png",
          "type": "Currency"
        },
        "amount": 200
      },
      {
        "item": {
          "id": 31070,
          "name": "Achievement Badge",
          "description": "Upon completion of this achievement, you will obtain a badge.",
          "icon": "/rw/assets/GLOBAL/ui/imagesets/items1//100543.png",
          "type": "Normal Item"
        },
        "amount": 1
      }
    ]
  },
  {
    "id": 0,
    "name": "Power of Skill",
    "description": "Upgrade 1 Doll's Skill to Lv.5",
    "group": "Growth",
    "points": 10,
    "rewards": [
      {
        "item": {
          "id": 35008,
          "name": "Soul",
          "description": "Crystallized by magic, it is necessary for any Witch who intends to sign a Soul Contract. $B$$B$Used to summon new Dolls",
          "icon": "/rw/assets/GLOBAL/ui/imagesets/items1//100191.png",
          "type": "Currency"
        },
        "amount": 80
      }
    ]
  },
  {
    "id": 0,
    "name": "Power of Skill",
    "description": "Upgrade 3 Dolls' Skills to Lv.5",
    "group": "Growth",
    "points": 10,
    "rewards": [
      {
        "item": {
          "id": 35008,
          "name": "Soul",
          "description": "Crystallized by magic, it is necessary for any Witch who intends to sign a Soul Contract. $B$$B$Used to summon new Dolls",
          "icon": "/rw/assets/GLOBAL/ui/imagesets/items1//100191.png",
          "type": "Currency"
        },
        "amount": 200
      }
    ]
  },
  {
    "id": 0,
    "name": "Fashion Icon",
    "description": "Obtain 1 Doll Costume",
    "group": "Bond",
    "points": 10,
    "rewards": [
      {
        "item": {
          "id": 35008,
          "name": "Soul",
          "description": "Crystallized by magic, it is necessary for any Witch who intends to sign a Soul Contract. $B$$B$Used to summon new Dolls",
          "icon": "/rw/assets/GLOBAL/ui/imagesets/items1//100191.png",
          "type": "Currency"
        },
        "amount": 40
      }
    ]
  },
  {
    "id": 0,
    "name": "Fashion Icon",
    "description": "Obtain 10 different Doll Costumes",
    "group": "Bond",
    "points": 10,
    "rewards": [
      {
        "item": {
          "id": 35008,
          "name": "Soul",
          "description": "Crystallized by magic, it is necessary for any Witch who intends to sign a Soul Contract. $B$$B$Used to summon new Dolls",
          "icon": "/rw/assets/GLOBAL/ui/imagesets/items1//100191.png",
          "type": "Currency"
        },
        "amount": 200
      }
    ]
  },
  {
    "id": 0,
    "name": "Forging Craft",
    "description": "1 piece of equipment reaches Lv.5",
    "group": "Growth",
    "points": 10,
    "rewards": [
      {
        "item": {
          "id": 35008,
          "name": "Soul",
          "description": "Crystallized by magic, it is necessary for any Witch who intends to sign a Soul Contract. $B$$B$Used to summon new Dolls",
          "icon": "/rw/assets/GLOBAL/ui/imagesets/items1//100191.png",
          "type": "Currency"
        },
        "amount": 40
      }
    ]
  },
  {
    "id": 0,
    "name": "Forging Craft",
    "description": "3 pieces equipment reach Lv.20",
    "group": "Growth",
    "points": 10,
    "rewards": [
      {
        "item": {
          "id": 35008,
          "name": "Soul",
          "description": "Crystallized by magic, it is necessary for any Witch who intends to sign a Soul Contract. $B$$B$Used to summon new Dolls",
          "icon": "/rw/assets/GLOBAL/ui/imagesets/items1//100191.png",
          "type": "Currency"
        },
        "amount": 80
      }
    ]
  },
  {
    "id": 0,
    "name": "Forging Craft",
    "description": "3 pieces equipment reach Lv.40",
    "group": "Growth",
    "points": 10,
    "rewards": [
      {
        "item": {
          "id": 35008,
          "name": "Soul",
          "description": "Crystallized by magic, it is necessary for any Witch who intends to sign a Soul Contract. $B$$B$Used to summon new Dolls",
          "icon": "/rw/assets/GLOBAL/ui/imagesets/items1//100191.png",
          "type": "Currency"
        },
        "amount": 200
      }
    ]
  },
  {
    "id": 0,
    "name": "Enchant Equipment",
    "description": "Enchant equipment 1 time",
    "group": "Growth",
    "points": 10,
    "rewards": [
      {
        "item": {
          "id": 35008,
          "name": "Soul",
          "description": "Crystallized by magic, it is necessary for any Witch who intends to sign a Soul Contract. $B$$B$Used to summon new Dolls",
          "icon": "/rw/assets/GLOBAL/ui/imagesets/items1//100191.png",
          "type": "Currency"
        },
        "amount": 40
      }
    ]
  },
  {
    "id": 0,
    "name": "Enchant Equipment",
    "description": "Enchant equipment 100 times",
    "group": "Growth",
    "points": 10,
    "rewards": [
      {
        "item": {
          "id": 35008,
          "name": "Soul",
          "description": "Crystallized by magic, it is necessary for any Witch who intends to sign a Soul Contract. $B$$B$Used to summon new Dolls",
          "icon": "/rw/assets/GLOBAL/ui/imagesets/items1//100191.png",
          "type": "Currency"
        },
        "amount": 80
      }
    ]
  },
  {
    "id": 0,
    "name": "Enchant Equipment",
    "description": "Enchant equipment 500 times",
    "group": "Growth",
    "points": 10,
    "rewards": [
      {
        "item": {
          "id": 35008,
          "name": "Soul",
          "description": "Crystallized by magic, it is necessary for any Witch who intends to sign a Soul Contract. $B$$B$Used to summon new Dolls",
          "icon": "/rw/assets/GLOBAL/ui/imagesets/items1//100191.png",
          "type": "Currency"
        },
        "amount": 200
      }
    ]
  },
  {
    "id": 0,
    "name": "Equipment Ascension",
    "description": "Ascend equipment 1 time",
    "group": "Growth",
    "points": 10,
    "rewards": [
      {
        "item": {
          "id": 35008,
          "name": "Soul",
          "description": "Crystallized by magic, it is necessary for any Witch who intends to sign a Soul Contract. $B$$B$Used to summon new Dolls",
          "icon": "/rw/assets/GLOBAL/ui/imagesets/items1//100191.png",
          "type": "Currency"
        },
        "amount": 40
      }
    ]
  },
  {
    "id": 0,
    "name": "Equipment Ascension",
    "description": "3 pieces equipment reach Ascension 2",
    "group": "Growth",
    "points": 10,
    "rewards": [
      {
        "item": {
          "id": 35008,
          "name": "Soul",
          "description": "Crystallized by magic, it is necessary for any Witch who intends to sign a Soul Contract. $B$$B$Used to summon new Dolls",
          "icon": "/rw/assets/GLOBAL/ui/imagesets/items1//100191.png",
          "type": "Currency"
        },
        "amount": 80
      }
    ]
  },
  {
    "id": 0,
    "name": "Equipment Ascension",
    "description": "3 pieces equipment reach Ascension 3",
    "group": "Growth",
    "points": 10,
    "rewards": [
      {
        "item": {
          "id": 35008,
          "name": "Soul",
          "description": "Crystallized by magic, it is necessary for any Witch who intends to sign a Soul Contract. $B$$B$Used to summon new Dolls",
          "icon": "/rw/assets/GLOBAL/ui/imagesets/items1//100191.png",
          "type": "Currency"
        },
        "amount": 200
      }
    ]
  },
  {
    "id": 32,
    "name": "Contact from the Otherworld",
    "description": "Have 10 friends",
    "group": "Social",
    "points": 10,
    "rewards": [
      {
        "item": {
          "id": 35008,
          "name": "Soul",
          "description": "Crystallized by magic, it is necessary for any Witch who intends to sign a Soul Contract. $B$$B$Used to summon new Dolls",
          "icon": "/rw/assets/GLOBAL/ui/imagesets/items1//100191.png",
          "type": "Currency"
        },
        "amount": 80
      },
      {
        "item": {
          "id": 31070,
          "name": "Achievement Badge",
          "description": "Upon completion of this achievement, you will obtain a badge.",
          "icon": "/rw/assets/GLOBAL/ui/imagesets/items1//100543.png",
          "type": "Normal Item"
        },
        "amount": 1
      }
    ]
  },
  {
    "id": 33,
    "name": "Contact from the Otherworld",
    "description": "Have 100 friends",
    "group": "Social",
    "points": 10,
    "rewards": [
      {
        "item": {
          "id": 35008,
          "name": "Soul",
          "description": "Crystallized by magic, it is necessary for any Witch who intends to sign a Soul Contract. $B$$B$Used to summon new Dolls",
          "icon": "/rw/assets/GLOBAL/ui/imagesets/items1//100191.png",
          "type": "Currency"
        },
        "amount": 500
      },
      {
        "item": {
          "id": 31070,
          "name": "Achievement Badge",
          "description": "Upon completion of this achievement, you will obtain a badge.",
          "icon": "/rw/assets/GLOBAL/ui/imagesets/items1//100543.png",
          "type": "Normal Item"
        },
        "amount": 1
      }
    ]
  },
  {
    "id": 0,
    "name": "The Heart of Friendship",
    "description": "Obtain 200 Friendship Points",
    "group": "Social",
    "points": 10,
    "rewards": [
      {
        "item": {
          "id": 35008,
          "name": "Soul",
          "description": "Crystallized by magic, it is necessary for any Witch who intends to sign a Soul Contract. $B$$B$Used to summon new Dolls",
          "icon": "/rw/assets/GLOBAL/ui/imagesets/items1//100191.png",
          "type": "Currency"
        },
        "amount": 40
      }
    ]
  },
  {
    "id": 0,
    "name": "The Heart of Friendship",
    "description": "Obtain 1,000 Friendship Points",
    "group": "Social",
    "points": 10,
    "rewards": [
      {
        "item": {
          "id": 35008,
          "name": "Soul",
          "description": "Crystallized by magic, it is necessary for any Witch who intends to sign a Soul Contract. $B$$B$Used to summon new Dolls",
          "icon": "/rw/assets/GLOBAL/ui/imagesets/items1//100191.png",
          "type": "Currency"
        },
        "amount": 80
      }
    ]
  },
  {
    "id": 0,
    "name": "The Heart of Friendship",
    "description": "Obtain 5,000 Friendship Points",
    "group": "Social",
    "points": 10,
    "rewards": [
      {
        "item": {
          "id": 35008,
          "name": "Soul",
          "description": "Crystallized by magic, it is necessary for any Witch who intends to sign a Soul Contract. $B$$B$Used to summon new Dolls",
          "icon": "/rw/assets/GLOBAL/ui/imagesets/items1//100191.png",
          "type": "Currency"
        },
        "amount": 200
      }
    ]
  },
  {
    "id": 0,
    "name": "Doll Collector",
    "description": "Summon 30 times",
    "group": "Bond",
    "points": 10,
    "rewards": [
      {
        "item": {
          "id": 35008,
          "name": "Soul",
          "description": "Crystallized by magic, it is necessary for any Witch who intends to sign a Soul Contract. $B$$B$Used to summon new Dolls",
          "icon": "/rw/assets/GLOBAL/ui/imagesets/items1//100191.png",
          "type": "Currency"
        },
        "amount": 40
      }
    ]
  },
  {
    "id": 0,
    "name": "Doll Collector",
    "description": "Summon 100 times",
    "group": "Bond",
    "points": 10,
    "rewards": [
      {
        "item": {
          "id": 35008,
          "name": "Soul",
          "description": "Crystallized by magic, it is necessary for any Witch who intends to sign a Soul Contract. $B$$B$Used to summon new Dolls",
          "icon": "/rw/assets/GLOBAL/ui/imagesets/items1//100191.png",
          "type": "Currency"
        },
        "amount": 80
      }
    ]
  },
  {
    "id": 0,
    "name": "Doll Collector",
    "description": "Summon 500 times",
    "group": "Bond",
    "points": 10,
    "rewards": [
      {
        "item": {
          "id": 35008,
          "name": "Soul",
          "description": "Crystallized by magic, it is necessary for any Witch who intends to sign a Soul Contract. $B$$B$Used to summon new Dolls",
          "icon": "/rw/assets/GLOBAL/ui/imagesets/items1//100191.png",
          "type": "Currency"
        },
        "amount": 200
      }
    ]
  },
  {
    "id": 0,
    "name": "Doll Collector",
    "description": "Summon 1,000 times",
    "group": "Bond",
    "points": 10,
    "rewards": [
      {
        "item": {
          "id": 35008,
          "name": "Soul",
          "description": "Crystallized by magic, it is necessary for any Witch who intends to sign a Soul Contract. $B$$B$Used to summon new Dolls",
          "icon": "/rw/assets/GLOBAL/ui/imagesets/items1//100191.png",
          "type": "Currency"
        },
        "amount": 500
      }
    ]
  },
  {
    "id": 0,
    "name": "The Value of Friendship",
    "description": "Purchase in Friendship Point Shop 50 times",
    "group": "Social",
    "points": 10,
    "rewards": [
      {
        "item": {
          "id": 35008,
          "name": "Soul",
          "description": "Crystallized by magic, it is necessary for any Witch who intends to sign a Soul Contract. $B$$B$Used to summon new Dolls",
          "icon": "/rw/assets/GLOBAL/ui/imagesets/items1//100191.png",
          "type": "Currency"
        },
        "amount": 40
      }
    ]
  },
  {
    "id": 0,
    "name": "The Value of Friendship",
    "description": "Purchase in Friendship Point Shop 100 times",
    "group": "Social",
    "points": 10,
    "rewards": [
      {
        "item": {
          "id": 35008,
          "name": "Soul",
          "description": "Crystallized by magic, it is necessary for any Witch who intends to sign a Soul Contract. $B$$B$Used to summon new Dolls",
          "icon": "/rw/assets/GLOBAL/ui/imagesets/items1//100191.png",
          "type": "Currency"
        },
        "amount": 200
      }
    ]
  },
  {
    "id": 0,
    "name": "Dream Maelstrom",
    "description": "Dream Maelstrom reaches max level 1 time",
    "group": "Growth",
    "points": 10,
    "rewards": [
      {
        "item": {
          "id": 35008,
          "name": "Soul",
          "description": "Crystallized by magic, it is necessary for any Witch who intends to sign a Soul Contract. $B$$B$Used to summon new Dolls",
          "icon": "/rw/assets/GLOBAL/ui/imagesets/items1//100191.png",
          "type": "Currency"
        },
        "amount": 40
      }
    ]
  },
  {
    "id": 0,
    "name": "Dream Maelstrom",
    "description": "Dream Maelstrom reaches Max. Lv 2 times",
    "group": "Growth",
    "points": 10,
    "rewards": [
      {
        "item": {
          "id": 35008,
          "name": "Soul",
          "description": "Crystallized by magic, it is necessary for any Witch who intends to sign a Soul Contract. $B$$B$Used to summon new Dolls",
          "icon": "/rw/assets/GLOBAL/ui/imagesets/items1//100191.png",
          "type": "Currency"
        },
        "amount": 80
      }
    ]
  },
  {
    "id": 0,
    "name": "Gathering Master",
    "description": "Obtain 100 Furniture Coins",
    "group": "Growth",
    "points": 10,
    "rewards": [
      {
        "item": {
          "id": 35008,
          "name": "Soul",
          "description": "Crystallized by magic, it is necessary for any Witch who intends to sign a Soul Contract. $B$$B$Used to summon new Dolls",
          "icon": "/rw/assets/GLOBAL/ui/imagesets/items1//100191.png",
          "type": "Currency"
        },
        "amount": 40
      }
    ]
  },
  {
    "id": 0,
    "name": "Gathering Master",
    "description": "Obtain 1,000 Furniture Coins",
    "group": "Growth",
    "points": 10,
    "rewards": [
      {
        "item": {
          "id": 35008,
          "name": "Soul",
          "description": "Crystallized by magic, it is necessary for any Witch who intends to sign a Soul Contract. $B$$B$Used to summon new Dolls",
          "icon": "/rw/assets/GLOBAL/ui/imagesets/items1//100191.png",
          "type": "Currency"
        },
        "amount": 80
      }
    ]
  },
  {
    "id": 0,
    "name": "Gathering Master",
    "description": "Obtain 5,000 Furniture Coins",
    "group": "Growth",
    "points": 10,
    "rewards": [
      {
        "item": {
          "id": 35008,
          "name": "Soul",
          "description": "Crystallized by magic, it is necessary for any Witch who intends to sign a Soul Contract. $B$$B$Used to summon new Dolls",
          "icon": "/rw/assets/GLOBAL/ui/imagesets/items1//100191.png",
          "type": "Currency"
        },
        "amount": 500
      }
    ]
  },
  {
    "id": 0,
    "name": "Mirror of the Otherworld",
    "description": "Explore Mirror of the Otherworld 1 time",
    "group": "Growth",
    "points": 10,
    "rewards": [
      {
        "item": {
          "id": 35008,
          "name": "Soul",
          "description": "Crystallized by magic, it is necessary for any Witch who intends to sign a Soul Contract. $B$$B$Used to summon new Dolls",
          "icon": "/rw/assets/GLOBAL/ui/imagesets/items1//100191.png",
          "type": "Currency"
        },
        "amount": 40
      }
    ]
  },
  {
    "id": 0,
    "name": "Mirror of the Otherworld",
    "description": "Explore Mirror of the Otherworld 20 times",
    "group": "Growth",
    "points": 10,
    "rewards": [
      {
        "item": {
          "id": 35008,
          "name": "Soul",
          "description": "Crystallized by magic, it is necessary for any Witch who intends to sign a Soul Contract. $B$$B$Used to summon new Dolls",
          "icon": "/rw/assets/GLOBAL/ui/imagesets/items1//100191.png",
          "type": "Currency"
        },
        "amount": 80
      }
    ]
  },
  {
    "id": 0,
    "name": "Mirror of the Otherworld",
    "description": "Explore Mirror of the Otherworld 100 times",
    "group": "Growth",
    "points": 10,
    "rewards": [
      {
        "item": {
          "id": 35008,
          "name": "Soul",
          "description": "Crystallized by magic, it is necessary for any Witch who intends to sign a Soul Contract. $B$$B$Used to summon new Dolls",
          "icon": "/rw/assets/GLOBAL/ui/imagesets/items1//100191.png",
          "type": "Currency"
        },
        "amount": 500
      }
    ]
  },
  {
    "id": 0,
    "name": "Alchemy",
    "description": "Perform alchemy 1 time",
    "group": "Growth",
    "points": 10,
    "rewards": [
      {
        "item": {
          "id": 35008,
          "name": "Soul",
          "description": "Crystallized by magic, it is necessary for any Witch who intends to sign a Soul Contract. $B$$B$Used to summon new Dolls",
          "icon": "/rw/assets/GLOBAL/ui/imagesets/items1//100191.png",
          "type": "Currency"
        },
        "amount": 40
      }
    ]
  },
  {
    "id": 0,
    "name": "Alchemy",
    "description": "Perform Alchemy 50 times",
    "group": "Growth",
    "points": 10,
    "rewards": [
      {
        "item": {
          "id": 35008,
          "name": "Soul",
          "description": "Crystallized by magic, it is necessary for any Witch who intends to sign a Soul Contract. $B$$B$Used to summon new Dolls",
          "icon": "/rw/assets/GLOBAL/ui/imagesets/items1//100191.png",
          "type": "Currency"
        },
        "amount": 80
      }
    ]
  },
  {
    "id": 0,
    "name": "Alchemy",
    "description": "Perform Alchemy 100 times",
    "group": "Growth",
    "points": 10,
    "rewards": [
      {
        "item": {
          "id": 35008,
          "name": "Soul",
          "description": "Crystallized by magic, it is necessary for any Witch who intends to sign a Soul Contract. $B$$B$Used to summon new Dolls",
          "icon": "/rw/assets/GLOBAL/ui/imagesets/items1//100191.png",
          "type": "Currency"
        },
        "amount": 200
      }
    ]
  },
  {
    "id": 24,
    "name": "Sweet Home",
    "description": "Fully upgrade all buildings in Witch Courtyard",
    "group": "Growth",
    "points": 10,
    "rewards": [
      {
        "item": {
          "id": 35008,
          "name": "Soul",
          "description": "Crystallized by magic, it is necessary for any Witch who intends to sign a Soul Contract. $B$$B$Used to summon new Dolls",
          "icon": "/rw/assets/GLOBAL/ui/imagesets/items1//100191.png",
          "type": "Currency"
        },
        "amount": 500
      },
      {
        "item": {
          "id": 31070,
          "name": "Achievement Badge",
          "description": "Upon completion of this achievement, you will obtain a badge.",
          "icon": "/rw/assets/GLOBAL/ui/imagesets/items1//100543.png",
          "type": "Normal Item"
        },
        "amount": 1
      }
    ]
  },
  {
    "id": 0,
    "name": "Furniture Theme",
    "description": "Apply 1 furniture theme",
    "group": "Growth",
    "points": 10,
    "rewards": [
      {
        "item": {
          "id": 35008,
          "name": "Soul",
          "description": "Crystallized by magic, it is necessary for any Witch who intends to sign a Soul Contract. $B$$B$Used to summon new Dolls",
          "icon": "/rw/assets/GLOBAL/ui/imagesets/items1//100191.png",
          "type": "Currency"
        },
        "amount": 40
      }
    ]
  },
  {
    "id": 0,
    "name": "Furniture Theme",
    "description": "Apply 5 different furniture themes",
    "group": "Growth",
    "points": 10,
    "rewards": [
      {
        "item": {
          "id": 35008,
          "name": "Soul",
          "description": "Crystallized by magic, it is necessary for any Witch who intends to sign a Soul Contract. $B$$B$Used to summon new Dolls",
          "icon": "/rw/assets/GLOBAL/ui/imagesets/items1//100191.png",
          "type": "Currency"
        },
        "amount": 80
      }
    ]
  },
  {
    "id": 0,
    "name": "Furniture Theme",
    "description": "Apply 10 different furniture themes",
    "group": "Growth",
    "points": 10,
    "rewards": [
      {
        "item": {
          "id": 35008,
          "name": "Soul",
          "description": "Crystallized by magic, it is necessary for any Witch who intends to sign a Soul Contract. $B$$B$Used to summon new Dolls",
          "icon": "/rw/assets/GLOBAL/ui/imagesets/items1//100191.png",
          "type": "Currency"
        },
        "amount": 500
      }
    ]
  },
  {
    "id": 0,
    "name": "The Broken Lands",
    "description": "Clear the Broken Lands 1 time",
    "group": "Growth",
    "points": 10,
    "rewards": [
      {
        "item": {
          "id": 35008,
          "name": "Soul",
          "description": "Crystallized by magic, it is necessary for any Witch who intends to sign a Soul Contract. $B$$B$Used to summon new Dolls",
          "icon": "/rw/assets/GLOBAL/ui/imagesets/items1//100191.png",
          "type": "Currency"
        },
        "amount": 40
      }
    ]
  },
  {
    "id": 0,
    "name": "The Broken Lands",
    "description": "Clear the Broken Lands 5 times",
    "group": "Growth",
    "points": 10,
    "rewards": [
      {
        "item": {
          "id": 35008,
          "name": "Soul",
          "description": "Crystallized by magic, it is necessary for any Witch who intends to sign a Soul Contract. $B$$B$Used to summon new Dolls",
          "icon": "/rw/assets/GLOBAL/ui/imagesets/items1//100191.png",
          "type": "Currency"
        },
        "amount": 80
      }
    ]
  },
  {
    "id": 0,
    "name": "The Broken Lands",
    "description": "Clear the Broken Lands for 20 times",
    "group": "Growth",
    "points": 10,
    "rewards": [
      {
        "item": {
          "id": 35008,
          "name": "Soul",
          "description": "Crystallized by magic, it is necessary for any Witch who intends to sign a Soul Contract. $B$$B$Used to summon new Dolls",
          "icon": "/rw/assets/GLOBAL/ui/imagesets/items1//100191.png",
          "type": "Currency"
        },
        "amount": 200
      }
    ]
  },
  {
    "id": 0,
    "name": "Chronospace Breach",
    "description": "Win in Chronospace Breach 10 times",
    "group": "Progress",
    "points": 10,
    "rewards": [
      {
        "item": {
          "id": 35008,
          "name": "Soul",
          "description": "Crystallized by magic, it is necessary for any Witch who intends to sign a Soul Contract. $B$$B$Used to summon new Dolls",
          "icon": "/rw/assets/GLOBAL/ui/imagesets/items1//100191.png",
          "type": "Currency"
        },
        "amount": 40
      }
    ]
  },
  {
    "id": 0,
    "name": "Chronospace Breach",
    "description": "Win in Chronospace Breach 100 times",
    "group": "Progress",
    "points": 10,
    "rewards": [
      {
        "item": {
          "id": 35008,
          "name": "Soul",
          "description": "Crystallized by magic, it is necessary for any Witch who intends to sign a Soul Contract. $B$$B$Used to summon new Dolls",
          "icon": "/rw/assets/GLOBAL/ui/imagesets/items1//100191.png",
          "type": "Currency"
        },
        "amount": 80
      }
    ]
  },
  {
    "id": 0,
    "name": "Chronospace Breach",
    "description": "Win in Chronospace Breach 500 times",
    "group": "Progress",
    "points": 10,
    "rewards": [
      {
        "item": {
          "id": 35008,
          "name": "Soul",
          "description": "Crystallized by magic, it is necessary for any Witch who intends to sign a Soul Contract. $B$$B$Used to summon new Dolls",
          "icon": "/rw/assets/GLOBAL/ui/imagesets/items1//100191.png",
          "type": "Currency"
        },
        "amount": 200
      }
    ]
  },
  {
    "id": 1,
    "name": "Recall Dreamland",
    "description": "Clear Dreamworld for the first time",
    "group": "Progress",
    "points": 10,
    "rewards": [
      {
        "item": {
          "id": 35008,
          "name": "Soul",
          "description": "Crystallized by magic, it is necessary for any Witch who intends to sign a Soul Contract. $B$$B$Used to summon new Dolls",
          "icon": "/rw/assets/GLOBAL/ui/imagesets/items1//100191.png",
          "type": "Currency"
        },
        "amount": 40
      },
      {
        "item": {
          "id": 31070,
          "name": "Achievement Badge",
          "description": "Upon completion of this achievement, you will obtain a badge.",
          "icon": "/rw/assets/GLOBAL/ui/imagesets/items1//100543.png",
          "type": "Normal Item"
        },
        "amount": 1
      }
    ]
  },
  {
    "id": 18,
    "name": "Thrive and Flourish",
    "description": "Magic Tree reaches Lv.3",
    "group": "Growth",
    "points": 10,
    "rewards": [
      {
        "item": {
          "id": 35008,
          "name": "Soul",
          "description": "Crystallized by magic, it is necessary for any Witch who intends to sign a Soul Contract. $B$$B$Used to summon new Dolls",
          "icon": "/rw/assets/GLOBAL/ui/imagesets/items1//100191.png",
          "type": "Currency"
        },
        "amount": 40
      },
      {
        "item": {
          "id": 31070,
          "name": "Achievement Badge",
          "description": "Upon completion of this achievement, you will obtain a badge.",
          "icon": "/rw/assets/GLOBAL/ui/imagesets/items1//100543.png",
          "type": "Normal Item"
        },
        "amount": 1
      }
    ]
  },
  {
    "id": 19,
    "name": "Quest Taker",
    "description": "Complete 10 quests",
    "group": "Progress",
    "points": 10,
    "rewards": [
      {
        "item": {
          "id": 35008,
          "name": "Soul",
          "description": "Crystallized by magic, it is necessary for any Witch who intends to sign a Soul Contract. $B$$B$Used to summon new Dolls",
          "icon": "/rw/assets/GLOBAL/ui/imagesets/items1//100191.png",
          "type": "Currency"
        },
        "amount": 40
      },
      {
        "item": {
          "id": 31070,
          "name": "Achievement Badge",
          "description": "Upon completion of this achievement, you will obtain a badge.",
          "icon": "/rw/assets/GLOBAL/ui/imagesets/items1//100543.png",
          "type": "Normal Item"
        },
        "amount": 1
      }
    ]
  },
  {
    "id": 20,
    "name": "Quest Taker",
    "description": "Complete 100 quests",
    "group": "Progress",
    "points": 10,
    "rewards": [
      {
        "item": {
          "id": 35008,
          "name": "Soul",
          "description": "Crystallized by magic, it is necessary for any Witch who intends to sign a Soul Contract. $B$$B$Used to summon new Dolls",
          "icon": "/rw/assets/GLOBAL/ui/imagesets/items1//100191.png",
          "type": "Currency"
        },
        "amount": 80
      },
      {
        "item": {
          "id": 31070,
          "name": "Achievement Badge",
          "description": "Upon completion of this achievement, you will obtain a badge.",
          "icon": "/rw/assets/GLOBAL/ui/imagesets/items1//100543.png",
          "type": "Normal Item"
        },
        "amount": 1
      }
    ]
  },
  {
    "id": 21,
    "name": "Quest Taker",
    "description": "Complete 200 quests",
    "group": "Progress",
    "points": 10,
    "rewards": [
      {
        "item": {
          "id": 35008,
          "name": "Soul",
          "description": "Crystallized by magic, it is necessary for any Witch who intends to sign a Soul Contract. $B$$B$Used to summon new Dolls",
          "icon": "/rw/assets/GLOBAL/ui/imagesets/items1//100191.png",
          "type": "Currency"
        },
        "amount": 500
      },
      {
        "item": {
          "id": 31070,
          "name": "Achievement Badge",
          "description": "Upon completion of this achievement, you will obtain a badge.",
          "icon": "/rw/assets/GLOBAL/ui/imagesets/items1//100543.png",
          "type": "Normal Item"
        },
        "amount": 1
      }
    ]
  },
  {
    "id": 25,
    "name": "Exploring the Unknown",
    "description": "Clear a stage for the first time",
    "group": "Progress",
    "points": 10,
    "rewards": [
      {
        "item": {
          "id": 35008,
          "name": "Soul",
          "description": "Crystallized by magic, it is necessary for any Witch who intends to sign a Soul Contract. $B$$B$Used to summon new Dolls",
          "icon": "/rw/assets/GLOBAL/ui/imagesets/items1//100191.png",
          "type": "Currency"
        },
        "amount": 40
      },
      {
        "item": {
          "id": 31070,
          "name": "Achievement Badge",
          "description": "Upon completion of this achievement, you will obtain a badge.",
          "icon": "/rw/assets/GLOBAL/ui/imagesets/items1//100543.png",
          "type": "Normal Item"
        },
        "amount": 1
      }
    ]
  },
  {
    "id": 26,
    "name": "Exploring the Unknown",
    "description": "Clear stages 50 times",
    "group": "Progress",
    "points": 10,
    "rewards": [
      {
        "item": {
          "id": 35008,
          "name": "Soul",
          "description": "Crystallized by magic, it is necessary for any Witch who intends to sign a Soul Contract. $B$$B$Used to summon new Dolls",
          "icon": "/rw/assets/GLOBAL/ui/imagesets/items1//100191.png",
          "type": "Currency"
        },
        "amount": 80
      },
      {
        "item": {
          "id": 31070,
          "name": "Achievement Badge",
          "description": "Upon completion of this achievement, you will obtain a badge.",
          "icon": "/rw/assets/GLOBAL/ui/imagesets/items1//100543.png",
          "type": "Normal Item"
        },
        "amount": 1
      }
    ]
  },
  {
    "id": 27,
    "name": "Exploring the Unknown",
    "description": "Clear stages 100 times",
    "group": "Progress",
    "points": 10,
    "rewards": [
      {
        "item": {
          "id": 35008,
          "name": "Soul",
          "description": "Crystallized by magic, it is necessary for any Witch who intends to sign a Soul Contract. $B$$B$Used to summon new Dolls",
          "icon": "/rw/assets/GLOBAL/ui/imagesets/items1//100191.png",
          "type": "Currency"
        },
        "amount": 500
      },
      {
        "item": {
          "id": 31070,
          "name": "Achievement Badge",
          "description": "Upon completion of this achievement, you will obtain a badge.",
          "icon": "/rw/assets/GLOBAL/ui/imagesets/items1//100543.png",
          "type": "Normal Item"
        },
        "amount": 1
      }
    ]
  },
  {
    "id": 0,
    "name": "Experience Sharing",
    "description": "Leave us a comment in App Store/GP store",
    "group": "Social",
    "points": 10,
    "rewards": [
      {
        "item": {
          "id": 35008,
          "name": "Soul",
          "description": "Crystallized by magic, it is necessary for any Witch who intends to sign a Soul Contract. $B$$B$Used to summon new Dolls",
          "icon": "/rw/assets/GLOBAL/ui/imagesets/items1//100191.png",
          "type": "Currency"
        },
        "amount": 40
      }
    ]
  },
  {
    "id": 0,
    "name": "Cassiel's Future",
    "description": "Defeat Camilyne",
    "group": "Progress",
    "points": 10,
    "rewards": [
      {
        "item": {
          "id": 35008,
          "name": "Soul",
          "description": "Crystallized by magic, it is necessary for any Witch who intends to sign a Soul Contract. $B$$B$Used to summon new Dolls",
          "icon": "/rw/assets/GLOBAL/ui/imagesets/items1//100191.png",
          "type": "Currency"
        },
        "amount": 80
      }
    ]
  },
  {
    "id": 0,
    "name": "Choice of Sword",
    "description": "Defeat Akasha",
    "group": "Progress",
    "points": 10,
    "rewards": [
      {
        "item": {
          "id": 35008,
          "name": "Soul",
          "description": "Crystallized by magic, it is necessary for any Witch who intends to sign a Soul Contract. $B$$B$Used to summon new Dolls",
          "icon": "/rw/assets/GLOBAL/ui/imagesets/items1//100191.png",
          "type": "Currency"
        },
        "amount": 80
      }
    ]
  }
]